mailoo/__init__.py
mailoo/__main__.py
mailoo/mailoo.py
mailoo/main.py
mailoo-1.0.2.dist-info/LICENSE
mailoo-1.0.2.dist-info/METADATA
mailoo-1.0.2.dist-info/WHEEL
mailoo-1.0.2.dist-info/top_level.txt
mailoo-1.0.2.dist-info/RECORD
