Metadata-Version: 2.1
Name: mailoo
Version: 1.0.2
Summary: Pacote para criaçao/envio de Emails, via SMTP protocolo.
Home-page: https://github.com/informeai/mailoo
Author: Wellington Gadelha
Author-email: contato.informeai@gmail.com
License: UNKNOWN
Platform: UNKNOWN
Classifier: Programming Language :: Python :: 3
Classifier: License :: OSI Approved :: MIT License
Classifier: Operating System :: OS Independent
Requires-Python: >=3.6
